verstr/__init__.py
verstr/_version.py
verstr-0.1.2.dist-info/LICENSE
verstr-0.1.2.dist-info/METADATA
verstr-0.1.2.dist-info/WHEEL
verstr-0.1.2.dist-info/top_level.txt
verstr-0.1.2.dist-info/zip-safe
verstr-0.1.2.dist-info/RECORD
