Metadata-Version: 2.1
Name: verstr
Version: 0.1.2
Summary: Make comparing version strings super simple.
Home-page: https://github.com/BRGM/verstr
Author: fsmai
Author-email: f.smai@brgm.fr
License: MIT
Project-URL: Documentation, https://github.com/BRGM/verstr#readme
Project-URL: Source code, https://github.com/BRGM/verstr
Project-URL: Issue Tracker, https://github.com/BRGM/verstr/issues
Platform: UNKNOWN
Classifier: Development Status :: 4 - Beta
Classifier: Intended Audience :: Developers
Classifier: License :: OSI Approved :: MIT License
Classifier: Programming Language :: Python :: 3 :: Only
Classifier: Topic :: Software Development :: Libraries
Classifier: Topic :: Utilities
Requires-Python: >=3.6
License-File: LICENSE
Requires-Dist: packaging
